CHANGELOG.txt
LICENSE.txt
MANIFEST.in
README.txt
setup.py
ceveri/__init__.py
ceveri.egg-info/PKG-INFO
ceveri.egg-info/SOURCES.txt
ceveri.egg-info/dependency_links.txt
ceveri.egg-info/requires.txt
ceveri.egg-info/top_level.txt