Metadata-Version: 2.1
Name: ceveri
Version: 1.0.3
Summary: Google Cloud API ile veri yerelleştirmesi amacıyla çeviri işlemleri gerçekleştiren bir kütüphane.
Home-page: https://ceveri.readthedocs.io
Author: Arda Uzunoğlu
Author-email: ardauzunogluarda@gmail.com
License: MIT
Platform: UNKNOWN
Classifier: Development Status :: 2 - Pre-Alpha
Classifier: Environment :: Console
Classifier: Intended Audience :: Science/Research
Classifier: Natural Language :: Turkish
Classifier: Operating System :: Microsoft :: Windows :: Windows 10
Classifier: License :: OSI Approved :: MIT License
Classifier: Programming Language :: Python :: 3
Classifier: Topic :: Text Processing
License-File: LICENSE.txt
